tirt
