Metadata-Version: 1.1
Name: tirt
Version: 0.0.6
Summary: the simulation of Thurstone Item Response Theory, include fixed forced test and adaptive forced test. 
Home-page: https://github.com/inuyasha2012/tirt
Author: inuyasha2012
Author-email: inuyasha021@163.com
License: MIT
Platform: UNKNOWN
Classifier: Programming Language :: Python :: 2.7
Classifier: Programming Language :: Python :: 3.6
